waveglow/__init__.py
waveglow/convert_model.py
waveglow/glow.py
waveglow/inference.py
waveglow/load.py
waveglow/mel2samp.py
waveglowpkg-0.0.2.dist-info/LICENSE
waveglowpkg-0.0.2.dist-info/METADATA
waveglowpkg-0.0.2.dist-info/WHEEL
waveglowpkg-0.0.2.dist-info/top_level.txt
waveglowpkg-0.0.2.dist-info/RECORD
