Metadata-Version: 2.1
Name: waveglowpkg
Version: 0.0.2
Summary: WaveGlow model to generate audio from mel-spectrograms
Home-page: https://waveglow.readthedocs.io/
Author: Essam
Author-email: essamwisam@outlook.com
Classifier: Intended Audience :: Developers
Classifier: License :: OSI Approved :: MIT License
Classifier: Programming Language :: Python
Classifier: Programming Language :: Python :: 3
Classifier: Programming Language :: Python :: 3.6
Classifier: Programming Language :: Python :: 3.7
Classifier: Programming Language :: Python :: 3.8
Classifier: Programming Language :: Python :: 3.9
Classifier: Operating System :: OS Independent
License-File: LICENSE
Requires-Dist: numpy
Requires-Dist: playsound
Requires-Dist: scipy
Requires-Dist: setuptools
Requires-Dist: torch
